modulegraph2/__init__.py
modulegraph2/__main__.py
modulegraph2/_ast_tools.py
modulegraph2/_bytecode_tools.py
modulegraph2/_callback_list.py
modulegraph2/_depinfo.py
modulegraph2/_distributions.py
modulegraph2/_dotbuilder.py
modulegraph2/_graphbuilder.py
modulegraph2/_htmlbuilder.py
modulegraph2/_implies.py
modulegraph2/_importinfo.py
modulegraph2/_modulegraph.py
modulegraph2/_nodes.py
modulegraph2/_swig_support.py
modulegraph2/_utilities.py
modulegraph2/_virtualenv_support.py
modulegraph2/py.typed
modulegraph2-2.2.1.dist-info/LICENSE.txt
modulegraph2-2.2.1.dist-info/WHEEL
modulegraph2-2.2.1.dist-info/METADATA
modulegraph2-2.2.1.dist-info/RECORD
