Metadata-Version: 2.1
Name: modulegraph2
Version: 2.2.1
Summary: A module import dependency graph for Python projects.
Home-page: https://modulegraph2.readthedocs.io/
License: MIT
Author: Ronald Oussoren
Author-email: ronaldoussoren@mac.com
Requires-Python: >=3.6,<4
Classifier: Intended Audience :: Developers
Classifier: License :: OSI Approved :: MIT License
Classifier: Programming Language :: Python :: 3 :: Only
Classifier: Programming Language :: Python :: 3
Classifier: Programming Language :: Python :: 3.6
Classifier: Programming Language :: Python :: 3.7
Classifier: Programming Language :: Python :: 3.8
Classifier: Programming Language :: Python :: 3.9
Classifier: Programming Language :: Python :: 3.10
Classifier: Programming Language :: Python :: 3.11
Classifier: Topic :: Software Development :: Libraries :: Python Modules
Classifier: Topic :: Software Development :: Build Tools
Classifier: Development Status :: 4 - Beta
Requires-Dist: typing_extensions
Requires-Dist: objectgraph
Requires-Dist: dataclasses; python_version < '3.7'
Project-URL: Documentation, https://modulegraph2.readthedocs.io/
Project-URL: Issue Tracker, https://github.com/ronaldoussoren/modulegraph2/issues
Project-URL: Source Code, https://github.com/ronaldoussoren/modulegraph2/
Project-URL: Supporting, https://blog.ronaldoussoren.net/support/
